drytools/__init__.py
drytools/decorator.py
drytools/decorator_factory.py
drytools/mixins.py
drytools/annotation/__init__.py
drytools/annotation/composition.py
drytools/annotation/functions.py
drytools-0.1.3.dist-info/METADATA
drytools-0.1.3.dist-info/RECORD
drytools-0.1.3.dist-info/WHEEL
drytools-0.1.3.dist-info/top_level.txt
