Metadata-Version: 2.1
Name: drytools
Version: 0.1.3
Summary: Tools for reducing repetition in Python code
Home-page: https://github.com/dan-elias/drytools
Author: Dan Elias
Author-email: daniel@elias-family.com
License: GPLv3
Download-URL: https://github.com/dan-elias/drytools/tarball/0.1.3
Platform: UNKNOWN
Classifier: Development Status :: 3 - Alpha
Classifier: Intended Audience :: Developers
Classifier: Programming Language :: Python :: 3
Classifier: License :: OSI Approved :: GNU General Public License v3 (GPLv3)
Classifier: Natural Language :: English
